aixplain/__init__.py
aixplain/cli_groups.py
aixplain/base/parameters.py
aixplain/decorators/__init__.py
aixplain/decorators/api_key_checker.py
aixplain/enums/__init__.py
aixplain/enums/asset_status.py
aixplain/enums/code_interpreter.py
aixplain/enums/data_split.py
aixplain/enums/data_subtype.py
aixplain/enums/data_type.py
aixplain/enums/database_source.py
aixplain/enums/embedding_model.py
aixplain/enums/error_handler.py
aixplain/enums/evolve_type.py
aixplain/enums/file_type.py
aixplain/enums/function.py
aixplain/enums/function_type.py
aixplain/enums/generated_enums.py
aixplain/enums/index_stores.py
aixplain/enums/language.py
aixplain/enums/license.py
aixplain/enums/onboard_status.py
aixplain/enums/ownership_type.py
aixplain/enums/privacy.py
aixplain/enums/response_status.py
aixplain/enums/sort_by.py
aixplain/enums/sort_order.py
aixplain/enums/splitting_options.py
aixplain/enums/status.py
aixplain/enums/storage_type.py
aixplain/enums/supplier.py
aixplain/exceptions/__init__.py
aixplain/exceptions/types.py
aixplain/factories/__init__.py
aixplain/factories/api_key_factory.py
aixplain/factories/asset_factory.py
aixplain/factories/benchmark_factory.py
aixplain/factories/corpus_factory.py
aixplain/factories/data_factory.py
aixplain/factories/dataset_factory.py
aixplain/factories/file_factory.py
aixplain/factories/integration_factory.py
aixplain/factories/metric_factory.py
aixplain/factories/script_factory.py
aixplain/factories/tool_factory.py
aixplain/factories/wallet_factory.py
aixplain/factories/agent_factory/__init__.py
aixplain/factories/agent_factory/utils.py
aixplain/factories/cli/model_factory_cli.py
aixplain/factories/finetune_factory/__init__.py
aixplain/factories/finetune_factory/prompt_validator.py
aixplain/factories/index_factory/__init__.py
aixplain/factories/index_factory/utils.py
aixplain/factories/model_factory/__init__.py
aixplain/factories/model_factory/utils.py
aixplain/factories/model_factory/mixins/__init__.py
aixplain-0.2.40.dist-info/METADATA
aixplain-0.2.40.dist-info/WHEEL
aixplain-0.2.40.dist-info/entry_points.txt
aixplain-0.2.40.dist-info/top_level.txt
aixplain-0.2.40.dist-info/RECORD
