Metadata-Version: 2.4
Name: aiXplain
Version: 0.2.40
Summary: aiXplain SDK adds AI functions to software.
Author-email: ahmet@aixplain.com, hadi@aixplain.com, kadir.pekel@aixplain.com, aina.abushaban@aixplain.com
License: Apache License, Version 2.0: http://www.apache.org/licenses/LICENSE-2.0
Project-URL: Homepage, https://github.com/aixplain/aiXplain
Project-URL: Documentation, https://github.com/aixplain/pipelines/tree/main/docs
Classifier: Development Status :: 2 - Pre-Alpha
Classifier: Environment :: Web Environment
Classifier: Intended Audience :: Developers
Classifier: License :: OSI Approved :: Apache Software License
Classifier: Natural Language :: English
Classifier: Operating System :: OS Independent
Classifier: Programming Language :: Python
Classifier: Programming Language :: Python :: 3
Classifier: Programming Language :: Python :: 3.10
Classifier: Programming Language :: Python :: 3.11
Classifier: Programming Language :: Python :: 3.12
Classifier: Programming Language :: Python :: 3 :: Only
Classifier: Programming Language :: Python :: Implementation :: CPython
Classifier: Programming Language :: Python :: Implementation :: PyPy
Classifier: Topic :: Internet :: WWW/HTTP
Classifier: Topic :: Software Development :: Libraries
Requires-Python: <4,>=3.9
Requires-Dist: requests>=2.1.0
Requires-Dist: tqdm>=4.1.0
Requires-Dist: pandas>=2.0.0
Requires-Dist: python-dotenv>=1.0.0
Requires-Dist: validators>=0.20.0
Requires-Dist: filetype>=1.2.0
Requires-Dist: click>=7.1.2
Requires-Dist: PyYAML>=6.0.1
Requires-Dist: dataclasses-json>=0.5.2
Requires-Dist: Jinja2==3.1.6
Requires-Dist: sentry-sdk>=1.0.0
Requires-Dist: pydantic>=2.10.6
Requires-Dist: filelock>=3.0.0
Provides-Extra: model-builder
Requires-Dist: model-interfaces~=0.0.2; extra == "model-builder"
Provides-Extra: test
Requires-Dist: pytest>=6.1.0; extra == "test"
Requires-Dist: docker>=6.1.3; extra == "test"
Requires-Dist: requests-mock>=1.11.0; extra == "test"
Requires-Dist: pytest-mock>=3.10.0; extra == "test"
Requires-Dist: pytest-rerunfailures>=16.0; extra == "test"
